{
  "processing_summary": {
    "total_targets_processed": 1,
    "total_target_texts": 12,
    "parameters": {
      "ocr_confidence_threshold": 0.3,
      "ignore_case": true,
      "text_match_mode": "exact"
    }
  },
  "results": [
    {
      "target_image": "Label.png",
      "total_matches": 9,
      "matches": [
        {
          "target_text": "ASSEMBLED IN VIETNAM",
          "detected_text": "ASSEMBLED IN VIETNAM",
          "confidence": 0.9168665613171533,
          "position": {
            "x": 99,
            "y": 383,
            "width": 206,
            "height": 20
          }
        },
        {
          "target_text": "AC ADAPTER",
          "detected_text": "AC ADAPTER",
          "confidence": 0.9995220828140033,
          "position": {
            "x": 21,
            "y": 265,
            "width": 108,
            "height": 20
          }
        },
        {
          "target_text": "OUTPUT (SALIDA): 18.0V 1.67A 30.0W",
          "detected_text": "OUTPUT (SALIDA): 18.0V =1.67A 30.OW & €",
          "confidence": 0.3769610111366381,
          "position": {
            "x": 11,
            "y": 325,
            "width": 362,
            "height": 20
          }
        },
        {
          "target_text": "VPPCCCUUYWWD####",
          "detected_text": "VPPCCCUUYWWD####",
          "confidence": 0.8365892133627381,
          "position": {
            "x": 107,
            "y": 403,
            "width": 190,
            "height": 20
          }
        },
        {
          "target_text": "EFICIENCIA ENERGÉTICA",
          "detected_text": "CAN ICES(B)INMB(B) EFICIENCIA ENERGÉTICA",
          "confidence": 0.9688279942583043,
          "position": {
            "x": 12,
            "y": 341,
            "width": 379,
            "height": 26
          }
        },
        {
          "target_text": "CUMPLE CON LA NOM-029-ENER-2017",
          "detected_text": "CUMPLE CON LA NOM-029-ENER-2017",
          "confidence": 0.9940978966018654,
          "position": {
            "x": 39,
            "y": 363,
            "width": 310,
            "height": 20
          }
        },
        {
          "target_text": "AMAZON.COM SERVICES LLC",
          "detected_text": "AMAZON COM SERVICES LLC",
          "confidence": 0.6704481691388857,
          "position": {
            "x": 144,
            "y": 264,
            "width": 241,
            "height": 21
          }
        },
        {
          "target_text": "CAUTION-ELECTRICALLY OPERATED PRODUCT",
          "detected_text": "CAUTION-ELECTRICALLY OPERATED   PRODUCT",
          "confidence": 0.6110510862945436,
          "position": {
            "x": 1,
            "y": 285,
            "width": 400,
            "height": 20
          }
        },
        {
          "target_text": "ATTENTION-PRODUIT À COMMANDE ÉLECTRIQUE",
          "detected_text": "ATTENTION-PRODUIT À COMMANDE ÉLECTRIQUE",
          "confidence": 0.9831818577569583,
          "position": {
            "x": 0,
            "y": 302,
            "width": 403,
            "height": 24
          }
        }
      ]
    }
  ]
}